[
  {
    "results": [
      {
        "id": 598,
        "pid": 598,
        "path": "IMG/7212.webp",
        "sort": 0
      },
      {
        "id": 623,
        "pid": 623,
        "path": "IMG/dt-2311.webp",
        "sort": 0
      },
      {
        "id": 624,
        "pid": 624,
        "path": "IMG/dt-2316.webp",
        "sort": 0
      },
      {
        "id": 625,
        "pid": 625,
        "path": "IMG/dt-2321.webp",
        "sort": 0
      },
      {
        "id": 626,
        "pid": 626,
        "path": "IMG/dt-2326.webp",
        "sort": 0
      },
      {
        "id": 627,
        "pid": 627,
        "path": "IMG/dt-2301.webp",
        "sort": 0
      },
      {
        "id": 628,
        "pid": 628,
        "path": "IMG/dt-2307.webp",
        "sort": 0
      },
      {
        "id": 629,
        "pid": 629,
        "path": "IMG/dt-2322.webp",
        "sort": 0
      },
      {
        "id": 630,
        "pid": 630,
        "path": "IMG/dt-2327.webp",
        "sort": 0
      },
      {
        "id": 631,
        "pid": 631,
        "path": "IMG/dt-2302.webp",
        "sort": 0
      },
      {
        "id": 632,
        "pid": 632,
        "path": "IMG/dt-2323.webp",
        "sort": 0
      },
      {
        "id": 633,
        "pid": 633,
        "path": "IMG/dt-2328.webp",
        "sort": 0
      },
      {
        "id": 634,
        "pid": 634,
        "path": "IMG/dt-2309.webp",
        "sort": 0
      },
      {
        "id": 635,
        "pid": 635,
        "path": "IMG/dt-2319.webp",
        "sort": 0
      },
      {
        "id": 636,
        "pid": 636,
        "path": "IMG/dt-2324.webp",
        "sort": 0
      },
      {
        "id": 637,
        "pid": 637,
        "path": "IMG/dt-2329.webp",
        "sort": 0
      },
      {
        "id": 638,
        "pid": 638,
        "path": "IMG/dt-2330.webp",
        "sort": 0
      },
      {
        "id": 643,
        "pid": 643,
        "path": "IMG/550171.webp",
        "sort": 0
      },
      {
        "id": 646,
        "pid": 646,
        "path": "IMG/550113.webp",
        "sort": 0
      },
      {
        "id": 647,
        "pid": 647,
        "path": "IMG/550175.webp",
        "sort": 0
      },
      {
        "id": 648,
        "pid": 648,
        "path": "IMG/550281.webp",
        "sort": 0
      },
      {
        "id": 649,
        "pid": 649,
        "path": "IMG/550231.webp",
        "sort": 0
      },
      {
        "id": 650,
        "pid": 650,
        "path": "IMG/550203.webp",
        "sort": 0
      },
      {
        "id": 651,
        "pid": 651,
        "path": "IMG/550252.webp",
        "sort": 0
      },
      {
        "id": 652,
        "pid": 652,
        "path": "IMG/550132.webp",
        "sort": 0
      },
      {
        "id": 653,
        "pid": 653,
        "path": "IMG/550282.webp",
        "sort": 0
      },
      {
        "id": 654,
        "pid": 654,
        "path": "IMG/550277.webp",
        "sort": 0
      },
      {
        "id": 655,
        "pid": 655,
        "path": "IMG/550205.webp",
        "sort": 0
      },
      {
        "id": 656,
        "pid": 656,
        "path": "IMG/550117.webp",
        "sort": 0
      },
      {
        "id": 657,
        "pid": 657,
        "path": "IMG/550253.webp",
        "sort": 0
      },
      {
        "id": 658,
        "pid": 658,
        "path": "IMG/550179.webp",
        "sort": 0
      },
      {
        "id": 659,
        "pid": 659,
        "path": "IMG/550283.webp",
        "sort": 0
      },
      {
        "id": 660,
        "pid": 660,
        "path": "IMG/550149.webp",
        "sort": 0
      },
      {
        "id": 661,
        "pid": 661,
        "path": "IMG/550278.webp",
        "sort": 0
      },
      {
        "id": 662,
        "pid": 662,
        "path": "IMG/550235.webp",
        "sort": 0
      },
      {
        "id": 663,
        "pid": 663,
        "path": "IMG/550207.webp",
        "sort": 0
      },
      {
        "id": 664,
        "pid": 664,
        "path": "IMG/550119.webp",
        "sort": 0
      },
      {
        "id": 665,
        "pid": 665,
        "path": "IMG/82-0050.webp",
        "sort": 0
      },
      {
        "id": 724,
        "pid": 724,
        "path": "IMG/п40889.webp",
        "sort": 0
      },
      {
        "id": 893,
        "pid": 893,
        "path": "IMG/р03030.webp",
        "sort": 0
      },
      {
        "id": 894,
        "pid": 894,
        "path": "IMG/р03053.webp",
        "sort": 0
      },
      {
        "id": 898,
        "pid": 898,
        "path": "IMG/р03031.webp",
        "sort": 0
      },
      {
        "id": 906,
        "pid": 906,
        "path": "IMG/р05216.webp",
        "sort": 0
      },
      {
        "id": 926,
        "pid": 926,
        "path": "IMG/р03025.webp",
        "sort": 0
      },
      {
        "id": 927,
        "pid": 927,
        "path": "IMG/р03025.webp",
        "sort": 0
      },
      {
        "id": 974,
        "pid": 974,
        "path": "IMG/р1529.webp",
        "sort": 0
      },
      {
        "id": 975,
        "pid": 975,
        "path": "IMG/р03036.webp",
        "sort": 0
      },
      {
        "id": 976,
        "pid": 976,
        "path": "IMG/р03036.webp",
        "sort": 0
      },
      {
        "id": 977,
        "pid": 977,
        "path": "IMG/р03038.webp",
        "sort": 0
      },
      {
        "id": 991,
        "pid": 991,
        "path": "IMG/03100.webp",
        "sort": 0
      },
      {
        "id": 1079,
        "pid": 1081,
        "path": "IMG/942110.webp",
        "sort": 0
      },
      {
        "id": 1151,
        "pid": 1153,
        "path": "IMG/п1404.webp",
        "sort": 0
      },
      {
        "id": 1158,
        "pid": 1160,
        "path": "IMG/8947.webp",
        "sort": 0
      },
      {
        "id": 1243,
        "pid": 1245,
        "path": "IMG/158101.webp",
        "sort": 0
      },
      {
        "id": 1244,
        "pid": 1246,
        "path": "IMG/158111.webp",
        "sort": 0
      },
      {
        "id": 1247,
        "pid": 1249,
        "path": "IMG/7388.webp",
        "sort": 0
      },
      {
        "id": 1251,
        "pid": 1253,
        "path": "IMG/1455.webp",
        "sort": 0
      },
      {
        "id": 1274,
        "pid": 1276,
        "path": "IMG/ge-1116.webp",
        "sort": 0
      },
      {
        "id": 1275,
        "pid": 1277,
        "path": "IMG/ge-1117.webp",
        "sort": 0
      },
      {
        "id": 1276,
        "pid": 1278,
        "path": "IMG/ge-1020.webp",
        "sort": 0
      },
      {
        "id": 1277,
        "pid": 1279,
        "path": "IMG/ge-1018.webp",
        "sort": 0
      },
      {
        "id": 1278,
        "pid": 1280,
        "path": "IMG/ge-1021.webp",
        "sort": 0
      },
      {
        "id": 1279,
        "pid": 1281,
        "path": "IMG/92-9314.webp",
        "sort": 0
      },
      {
        "id": 1280,
        "pid": 1282,
        "path": "IMG/551161.webp",
        "sort": 0
      },
      {
        "id": 1281,
        "pid": 1283,
        "path": "IMG/551162.webp",
        "sort": 0
      },
      {
        "id": 1282,
        "pid": 1284,
        "path": "IMG/551163.webp",
        "sort": 0
      },
      {
        "id": 1283,
        "pid": 1285,
        "path": "IMG/551164.webp",
        "sort": 0
      },
      {
        "id": 1298,
        "pid": 1300,
        "path": "IMG/80057080.webp",
        "sort": 0
      },
      {
        "id": 1299,
        "pid": 1301,
        "path": "IMG/ge-1013.webp",
        "sort": 0
      },
      {
        "id": 1300,
        "pid": 1302,
        "path": "IMG/ge-1113.webp",
        "sort": 0
      },
      {
        "id": 1301,
        "pid": 1303,
        "path": "IMG/ge-1015.webp",
        "sort": 0
      },
      {
        "id": 1302,
        "pid": 1304,
        "path": "IMG/ge-1115.webp",
        "sort": 0
      },
      {
        "id": 1303,
        "pid": 1305,
        "path": "IMG/ge-1114.webp",
        "sort": 0
      },
      {
        "id": 1304,
        "pid": 1306,
        "path": "IMG/92-9317.webp",
        "sort": 0
      },
      {
        "id": 1305,
        "pid": 1307,
        "path": "IMG/551151.webp",
        "sort": 0
      },
      {
        "id": 1306,
        "pid": 1308,
        "path": "IMG/551156.webp",
        "sort": 0
      },
      {
        "id": 1307,
        "pid": 1309,
        "path": "IMG/551153.webp",
        "sort": 0
      },
      {
        "id": 1308,
        "pid": 1310,
        "path": "IMG/551155.webp",
        "sort": 0
      },
      {
        "id": 1309,
        "pid": 1311,
        "path": "IMG/551152.webp",
        "sort": 0
      },
      {
        "id": 1310,
        "pid": 1312,
        "path": "IMG/551154.webp",
        "sort": 0
      },
      {
        "id": 1317,
        "pid": 1319,
        "path": "IMG/ge-2003.webp",
        "sort": 0
      },
      {
        "id": 1712,
        "pid": 1714,
        "path": "IMG/ge-0054.webp",
        "sort": 0
      },
      {
        "id": 1713,
        "pid": 1715,
        "path": "IMG/ge-0051.webp",
        "sort": 0
      },
      {
        "id": 1715,
        "pid": 1717,
        "path": "IMG/92-9332.webp",
        "sort": 0
      },
      {
        "id": 1716,
        "pid": 1718,
        "path": "IMG/ge-0065.webp",
        "sort": 0
      },
      {
        "id": 1721,
        "pid": 1723,
        "path": "IMG/ge-0015.webp",
        "sort": 0
      },
      {
        "id": 1722,
        "pid": 1724,
        "path": "IMG/92-9301.webp",
        "sort": 0
      },
      {
        "id": 1725,
        "pid": 1727,
        "path": "IMG/ge-1510.webp",
        "sort": 0
      },
      {
        "id": 1728,
        "pid": 1730,
        "path": "IMG/ge-0021.webp",
        "sort": 0
      },
      {
        "id": 1729,
        "pid": 1731,
        "path": "IMG/ge-0030.webp",
        "sort": 0
      },
      {
        "id": 1730,
        "pid": 1732,
        "path": "IMG/551221.webp",
        "sort": 0
      },
      {
        "id": 1731,
        "pid": 1733,
        "path": "IMG/551222.webp",
        "sort": 0
      },
      {
        "id": 1735,
        "pid": 1737,
        "path": "IMG/6 700.webp",
        "sort": 0
      },
      {
        "id": 1736,
        "pid": 1738,
        "path": "IMG/ft-9005.webp",
        "sort": 0
      },
      {
        "id": 1737,
        "pid": 1739,
        "path": "IMG/101428.webp",
        "sort": 0
      },
      {
        "id": 1738,
        "pid": 1740,
        "path": "IMG/5004334.webp",
        "sort": 0
      },
      {
        "id": 1739,
        "pid": 1741,
        "path": "IMG/5004354.webp",
        "sort": 0
      },
      {
        "id": 1740,
        "pid": 1742,
        "path": "IMG/6 700.webp",
        "sort": 0
      },
      {
        "id": 1741,
        "pid": 1743,
        "path": "IMG/551225.webp",
        "sort": 0
      },
      {
        "id": 1742,
        "pid": 1744,
        "path": "IMG/ge-0001.webp",
        "sort": 0
      },
      {
        "id": 1743,
        "pid": 1745,
        "path": "IMG/ат-084.webp",
        "sort": 0
      },
      {
        "id": 1879,
        "pid": 1881,
        "path": "IMG/р1544.webp",
        "sort": 0
      },
      {
        "id": 1891,
        "pid": 1893,
        "path": "IMG/8801.webp",
        "sort": 0
      },
      {
        "id": 1892,
        "pid": 1894,
        "path": "IMG/8800.webp",
        "sort": 0
      },
      {
        "id": 1893,
        "pid": 1895,
        "path": "IMG/8801.webp",
        "sort": 0
      },
      {
        "id": 1894,
        "pid": 1896,
        "path": "IMG/8801.webp",
        "sort": 0
      },
      {
        "id": 1895,
        "pid": 1897,
        "path": "IMG/8825.webp",
        "sort": 0
      },
      {
        "id": 2006,
        "pid": 2008,
        "path": "IMG/14472.webp",
        "sort": 0
      },
      {
        "id": 2007,
        "pid": 2009,
        "path": "IMG/м216.webp",
        "sort": 0
      },
      {
        "id": 2008,
        "pid": 2010,
        "path": "IMG/ft-2010.webp",
        "sort": 0
      },
      {
        "id": 2009,
        "pid": 2011,
        "path": "IMG/ft-3004.webp",
        "sort": 0
      },
      {
        "id": 2010,
        "pid": 2012,
        "path": "IMG/11006.webp",
        "sort": 0
      },
      {
        "id": 2011,
        "pid": 2013,
        "path": "IMG/ft-3002.webp",
        "sort": 0
      },
      {
        "id": 2021,
        "pid": 2023,
        "path": "IMG/6 624.webp",
        "sort": 0
      },
      {
        "id": 2024,
        "pid": 2026,
        "path": "IMG/30348.webp",
        "sort": 0
      },
      {
        "id": 2028,
        "pid": 2030,
        "path": "IMG/ft-2003.webp",
        "sort": 0
      },
      {
        "id": 2029,
        "pid": 2031,
        "path": "IMG/ft-2000.webp",
        "sort": 0
      },
      {
        "id": 2030,
        "pid": 2032,
        "path": "IMG/45-411.webp",
        "sort": 0
      },
      {
        "id": 2031,
        "pid": 2033,
        "path": "IMG/14-6255.webp",
        "sort": 0
      },
      {
        "id": 2032,
        "pid": 2034,
        "path": "IMG/14-6188.webp",
        "sort": 0
      },
      {
        "id": 2036,
        "pid": 2038,
        "path": "IMG/400362.webp",
        "sort": 0
      },
      {
        "id": 2042,
        "pid": 2044,
        "path": "IMG/14-6176.webp",
        "sort": 0
      },
      {
        "id": 2044,
        "pid": 2046,
        "path": "IMG/с023.webp",
        "sort": 0
      },
      {
        "id": 2047,
        "pid": 2049,
        "path": "IMG/45-413.webp",
        "sort": 0
      },
      {
        "id": 2048,
        "pid": 2050,
        "path": "IMG/14-6130.webp",
        "sort": 0
      },
      {
        "id": 2049,
        "pid": 2051,
        "path": "IMG/14-6131.webp",
        "sort": 0
      },
      {
        "id": 2051,
        "pid": 2053,
        "path": "IMG/3142.webp",
        "sort": 0
      },
      {
        "id": 2052,
        "pid": 2054,
        "path": "IMG/ht-3144.webp",
        "sort": 0
      },
      {
        "id": 2053,
        "pid": 2055,
        "path": "IMG/3150.webp",
        "sort": 0
      },
      {
        "id": 2054,
        "pid": 2056,
        "path": "IMG/550395.webp",
        "sort": 0
      },
      {
        "id": 2055,
        "pid": 2057,
        "path": "IMG/14-6019.webp",
        "sort": 0
      },
      {
        "id": 2067,
        "pid": 2069,
        "path": "IMG/ср170.webp",
        "sort": 0
      },
      {
        "id": 2068,
        "pid": 2070,
        "path": "IMG/мл90.webp",
        "sort": 0
      },
      {
        "id": 2071,
        "pid": 2073,
        "path": "IMG/45-419.webp",
        "sort": 0
      },
      {
        "id": 2072,
        "pid": 2075,
        "path": "IMG/14-6177.webp",
        "sort": 0
      },
      {
        "id": 2077,
        "pid": 2080,
        "path": "IMG/sp-0163.webp",
        "sort": 0
      },
      {
        "id": 2081,
        "pid": 2084,
        "path": "IMG/ft-1000.webp",
        "sort": 0
      },
      {
        "id": 2082,
        "pid": 2085,
        "path": "IMG/ft-1003.webp",
        "sort": 0
      },
      {
        "id": 2083,
        "pid": 2086,
        "path": "IMG/ft-1005.webp",
        "sort": 0
      },
      {
        "id": 2084,
        "pid": 2087,
        "path": "IMG/ft-1014.webp",
        "sort": 0
      },
      {
        "id": 2085,
        "pid": 2088,
        "path": "IMG/ft-1012.webp",
        "sort": 0
      },
      {
        "id": 2088,
        "pid": 2091,
        "path": "IMG/14-6124.webp",
        "sort": 0
      },
      {
        "id": 2094,
        "pid": 2097,
        "path": "IMG/482018631.webp",
        "sort": 0
      },
      {
        "id": 2098,
        "pid": 2101,
        "path": "IMG/14-6150.webp",
        "sort": 0
      },
      {
        "id": 2100,
        "pid": 2103,
        "path": "IMG/ft-1107.webp",
        "sort": 0
      },
      {
        "id": 2103,
        "pid": 2106,
        "path": "IMG/7622.webp",
        "sort": 0
      },
      {
        "id": 2104,
        "pid": 2107,
        "path": "IMG/7622.webp",
        "sort": 0
      },
      {
        "id": 2105,
        "pid": 2108,
        "path": "IMG/7623.webp",
        "sort": 0
      },
      {
        "id": 2106,
        "pid": 2109,
        "path": "IMG/7623.webp",
        "sort": 0
      },
      {
        "id": 2259,
        "pid": 2262,
        "path": "IMG/47328.webp",
        "sort": 0
      },
      {
        "id": 2260,
        "pid": 2263,
        "path": "IMG/47349.webp",
        "sort": 0
      },
      {
        "id": 2261,
        "pid": 2264,
        "path": "IMG/47404.webp",
        "sort": 0
      }
    ],
    "success": true,
    "meta": {
      "served_by": "v3-prod",
      "served_by_region": "EEUR",
      "served_by_colo": "WAW",
      "served_by_primary": true,
      "timings": {
        "sql_duration_ms": 1.0674
      },
      "duration": 1.0674,
      "changes": 0,
      "last_row_id": 0,
      "changed_db": false,
      "size_after": 3284992,
      "rows_read": 456,
      "rows_written": 0,
      "total_attempts": 1
    }
  }
]
